pytest_mypy_plugins_shim-0.2.0.dist-info/WHEEL
pytest_mypy_plugins_shim-0.2.0.dist-info/entry_points.txt
pytest_mypy_plugins_shim-0.2.0.dist-info/METADATA
pytest_mypy_plugins_shim-0.2.0.dist-info/top_level.txt
pytest_mypy_plugins_shim-0.2.0.dist-info/LICENSE
pytest_mypy_plugins_shim/__init__.py
pytest_mypy_plugins_shim-0.2.0.dist-info/RECORD
