Metadata-Version: 2.1
Name: pytest-mypy-plugins-shim
Version: 0.2.0
Summary: Substitute for "pytest-mypy-plugins" for Python implementations which aren't supported by mypy.
Author-email: Dominic Davis-Foster <dominic@davis-foster.co.uk>
License: MIT
Home-page: https://github.com/python-coincidence/pytest-mypy-plugins-shim
Project-URL: Issue Tracker, https://github.com/python-coincidence/pytest-mypy-plugins-shim/issues
Project-URL: Source Code, https://github.com/python-coincidence/pytest-mypy-plugins-shim
Platform: Windows
Platform: macOS
Platform: Linux
Classifier: License :: OSI Approved :: MIT License
Classifier: Operating System :: OS Independent
Classifier: Programming Language :: Python
Classifier: Programming Language :: Python :: 3 :: Only
Classifier: Programming Language :: Python :: 3.6
Classifier: Programming Language :: Python :: 3.7
Classifier: Programming Language :: Python :: Implementation :: PyPy
Requires-Python: >=3.6
Requires-Dist: pytest>=6.0.0
